kivy_tetris_package/__init__.py
kivy_tetris_package/main.py
kivy_tetris_package/tetris.kv
kivy_tetris_package-0.51.dist-info/LICENSE
kivy_tetris_package-0.51.dist-info/METADATA
kivy_tetris_package-0.51.dist-info/WHEEL
kivy_tetris_package-0.51.dist-info/entry_points.txt
kivy_tetris_package-0.51.dist-info/top_level.txt
kivy_tetris_package-0.51.dist-info/RECORD
