Metadata-Version: 2.1
Name: kivy-tetris-package
Version: 0.51
Summary: Tetris game written in Kivy
Home-page: UNKNOWN
Author: Daniel Kříž
License: MIT
Platform: UNKNOWN
Requires-Python: >=3.6
License-File: LICENSE
Requires-Dist: kivy
